dicom_mcp/__init__.py
dicom_mcp/__main__.py
dicom_mcp/attributes.py
dicom_mcp/config.py
dicom_mcp/dicom_client.py
dicom_mcp/server.py
dicom_mcp-0.1.1.dist-info/licenses/LICENSE
dicom_mcp-0.1.1.dist-info/METADATA
dicom_mcp-0.1.1.dist-info/WHEEL
dicom_mcp-0.1.1.dist-info/entry_points.txt
dicom_mcp-0.1.1.dist-info/top_level.txt
dicom_mcp-0.1.1.dist-info/RECORD
